[
    {
        "MD5": "e66d6290ad8aad7cdbde78bd460c9563",
        "frecventa": " ",
        "materie": "Limba engleza IV",
        "ora": "08:00-10:00",
        "pachet": " ",
        "profesori": [
            "Armanu Nicoleta"
        ],
        "sala": [
            "C909"
        ],
        "tip": "Seminar"
    },
    {
        "MD5": "c30e066701cc267cca6e9eabfb722ef6",
        "frecventa": " ",
        "materie": "Antreprenoriat si inovare in IT",
        "ora": "12:00-14:00",
        "pachet": "1",
        "profesori": [
            "Conf.dr. Forascu Corina"
        ],
        "sala": [
            "C309"
        ],
        "tip": "Curs"
    },
    {
        "MD5": "2445c9e04a1454be07a2e2b93e9ec42a",
        "frecventa": " ",
        "materie": "Antreprenoriat si inovare in IT",
        "ora": "14:00-16:00",
        "pachet": "1",
        "profesori": [
            "Conf.dr. Forascu Corina"
        ],
        "sala": [
            "C905"
        ],
        "tip": "Seminar"
    },
    {
        "MD5": "48202add520a7cb50f57343abe21dae8",
        "frecventa": " ",
        "materie": "Modele continue si Matlab",
        "ora": "14:00-16:00",
        "pachet": "1",
        "profesori": [
            "Lect.dr. Iacob Florin"
        ],
        "sala": [
            "C2"
        ],
        "tip": "Consultatii"
    },
    {
        "MD5": "4ce662ab58dbdd76bb7a3fd45defe92e",
        "frecventa": " ",
        "materie": "Programare functionala",
        "ora": "14:00-16:00",
        "pachet": "1",
        "profesori": [
            "Conf. dr. Ciobaca Stefan"
        ],
        "sala": [
            "C112"
        ],
        "tip": "Curs"
    },
    {
        "MD5": "4c1627b471a1435698ba88a8f8ef3ff8",
        "frecventa": " ",
        "materie": "Practica SGBD",
        "ora": "16:00-18:00",
        "pachet": " ",
        "profesori": [
            "Colab. Dr. Spiridonica Alexandru"
        ],
        "sala": [
            "C401"
        ],
        "tip": "Laborator"
    }
]